awsdeleter/__init__.py
awsdeleter/awsdeleter.py
awsdeleter-0.1.3.dist-info/licenses/LICENSE
awsdeleter-0.1.3.dist-info/METADATA
awsdeleter-0.1.3.dist-info/WHEEL
awsdeleter-0.1.3.dist-info/entry_points.txt
awsdeleter-0.1.3.dist-info/top_level.txt
awsdeleter-0.1.3.dist-info/RECORD
