Metadata-Version: 2.4
Name: awsdeleter
Version: 0.1.3
Summary: A CLI tool to search and delete AWS EC2, S3, and VPC resources by prefix
Author: Omkar Khatavkar
Author-email: okhatavkar007@gmail.com
License: MIT
Classifier: Programming Language :: Python :: 3
Classifier: License :: OSI Approved :: MIT License
Classifier: Operating System :: OS Independent
Requires-Python: >=3.6
License-File: LICENSE
Requires-Dist: boto3
Requires-Dist: click
Dynamic: author
Dynamic: author-email
Dynamic: classifier
Dynamic: description
Dynamic: description-content-type
Dynamic: license
Dynamic: license-file
Dynamic: requires-dist
Dynamic: requires-python
Dynamic: summary
